{"name":"Duditest","body":"#First title\r\n\r\nThis is my first GitHub page.\r\n\r\n`<h1>Testing</h1>`\r\n\r\n1. List 1\r\n2. List 2\r\n3. List 3\r\n\r\n##Subtitle\r\n***\r\n\r\n* Li 1\r\n* Li 2\r\n\r\n> Quote\r\n\r\n```\r\n\t\t\t<div class=\"contentLeft\">\r\n\t\t\t\t<h2><strong>Boards:</strong></h2>\r\n\t\t\t\t<ul class=\"links\">\r\n\t\t\t\t\t<li><a href=\"http://www.fanatic.com\" onclick=\"window.open(this.href,'','');return false;\" class=\"logoFanatic\" title=\"Fanatic\">Fanatic</a></li>\r\n\t\t\t\t\t<li><a href=\"http://goyawindsurfing.com\" onclick=\"window.open(this.href,'','');return false;\" class=\"logoGoya\" title=\"Goya\">Goya</a></li>\r\n\t\t\t\t\t<li><a href=\"http://www.jp-australia.com\" onclick=\"window.open(this.href,'','');return false;\" class=\"logoJPAustralia\" title=\"JP-Australia\">JP-Australia</a></li>\r\n\t\t\t\t\t<li><a href=\"http://quatrointernational.com\" onclick=\"window.open(this.href,'','');return false;\" class=\"logoQuatro\" title=\"Quatro\">Quatro</a></li>\r\n\t\t\t\t\t<li><a href=\"http://www.robertoriccidesigns.com\" onclick=\"window.open(this.href,'','');return false;\" class=\"logoRrd\" title=\"RRD\">RRD</a></li>\r\n\t\t\t\t\t<li><a href=\"http://www.simmerstyle.eu\" onclick=\"window.open(this.href,'','');return false;\" class=\"logoSimmerSails\" title=\"Simmer\">Simmer</a></li>\r\n\t\t\t\t\t<li><a href=\"http://www.star-board.com\" onclick=\"window.open(this.href,'','');return false;\" class=\"logoStarboard\" title=\"Starboard\">Starboard</a></li>\r\n\t\t\t\t\t<li><a href=\"http://www.tabou-boards.com\" onclick=\"window.open(this.href,'','');return false;\" class=\"logoTabou\" title=\"Tabou\">Tabou</a></li>\r\n\t\t\t\t\t<li><a href=\"\" onclick=\"window.open(this.href,'','');return false;\" class=\"logoTabou\" title=\"Witchcraft\">Witchcraft</a></li>\r\n\t\t\t\t</ul>\r\n\t\t\t</div>\r\n```","tagline":"","google":"","note":"Don't delete this file! It's used internally to help with page regeneration."}